README
eventable.py
eventhook.py
setup.py
bigsignal.egg-info/PKG-INFO
bigsignal.egg-info/SOURCES.txt
bigsignal.egg-info/dependency_links.txt
bigsignal.egg-info/top_level.txt