Metadata-Version: 1.0
Name: bigsignal
Version: 0.0.1
Summary: simple evented objects
Home-page: https://github.com/rranshous/bigsignal
Author: Robby Ranshous
Author-email: rranshous@gmail.com
License: UNKNOWN
Keywords: event
Platform: UNKNOWN
Classifier: Development Status :: 3 - Alpha
Classifier: Programming Language :: Python :: 2.6
Classifier: Programming Language :: Python :: 2.7
